.nojekyll
LICENSE
README.md
pyproject.toml
setup.py
docs/conf.py
docs/index.rst
html/index.html
html/objects.inv
html/_static/images/logo_binder.svg
html/_static/images/logo_colab.png
html/_static/images/logo_deepnote.svg
html/_static/images/logo_jupyterhub.svg
html/_static/locales/ar/LC_MESSAGES/booktheme.mo
html/_static/locales/ar/LC_MESSAGES/booktheme.po
html/_static/locales/bg/LC_MESSAGES/booktheme.mo
html/_static/locales/bg/LC_MESSAGES/booktheme.po
html/_static/locales/bn/LC_MESSAGES/booktheme.mo
html/_static/locales/bn/LC_MESSAGES/booktheme.po
html/_static/locales/ca/LC_MESSAGES/booktheme.mo
html/_static/locales/ca/LC_MESSAGES/booktheme.po
html/_static/locales/cs/LC_MESSAGES/booktheme.mo
html/_static/locales/cs/LC_MESSAGES/booktheme.po
html/_static/locales/da/LC_MESSAGES/booktheme.mo
html/_static/locales/da/LC_MESSAGES/booktheme.po
html/_static/locales/de/LC_MESSAGES/booktheme.mo
html/_static/locales/de/LC_MESSAGES/booktheme.po
html/_static/locales/el/LC_MESSAGES/booktheme.mo
html/_static/locales/el/LC_MESSAGES/booktheme.po
html/_static/locales/eo/LC_MESSAGES/booktheme.mo
html/_static/locales/eo/LC_MESSAGES/booktheme.po
html/_static/locales/es/LC_MESSAGES/booktheme.mo
html/_static/locales/es/LC_MESSAGES/booktheme.po
html/_static/locales/et/LC_MESSAGES/booktheme.mo
html/_static/locales/et/LC_MESSAGES/booktheme.po
html/_static/locales/fi/LC_MESSAGES/booktheme.mo
html/_static/locales/fi/LC_MESSAGES/booktheme.po
html/_static/locales/fr/LC_MESSAGES/booktheme.mo
html/_static/locales/fr/LC_MESSAGES/booktheme.po
html/_static/locales/hr/LC_MESSAGES/booktheme.mo
html/_static/locales/hr/LC_MESSAGES/booktheme.po
html/_static/locales/id/LC_MESSAGES/booktheme.mo
html/_static/locales/id/LC_MESSAGES/booktheme.po
html/_static/locales/it/LC_MESSAGES/booktheme.mo
html/_static/locales/it/LC_MESSAGES/booktheme.po
html/_static/locales/iw/LC_MESSAGES/booktheme.mo
html/_static/locales/iw/LC_MESSAGES/booktheme.po
html/_static/locales/ja/LC_MESSAGES/booktheme.mo
src/pjz.egg-info/PKG-INFO
src/pjz.egg-info/SOURCES.txt
src/pjz.egg-info/dependency_links.txt
src/pjz.egg-info/requires.txt
src/pjz.egg-info/top_level.txt
