Metadata-Version: 2.1
Name: pjz
Version: 0.0.2
Summary: pjz is JAX and fdtd-z.
Home-page: https://github.com/spinsphotonics/pjz
Author: Jesse Lu
Author-email: jesselu@spinsphotonics.com
License: MIT
Platform: UNKNOWN
Provides-Extra: test
License-File: LICENSE
